sportify/__init__.py
sportify/main.py
sportify/meta.py
sportify/sportify.py
sportify-0.9.0.dist-info/METADATA
sportify-0.9.0.dist-info/WHEEL
sportify-0.9.0.dist-info/entry_points.txt
sportify-0.9.0.dist-info/licenses/LICENSE
sportify-0.9.0.dist-info/RECORD
