Metadata-Version: 2.3
Name: sportify
Version: 0.9.0
Summary: Fetch sports data from CLI
Project-URL: Homepage, https://github.com/jacob-thompson/sportify
Project-URL: Bug Reports, https://github.com/jacob-thompson/sportify/issues
Author-email: "Jacob A. Thompson" <jacobalthompson@gmail.com>
Maintainer-email: "Jacob A. Thompson" <jacobalthompson@gmail.com>
License: MIT License
Keywords: application,athletics,cli,data,espn,executable,sports
Classifier: Development Status :: 5 - Production/Stable
Classifier: License :: OSI Approved :: MIT License
Classifier: Programming Language :: Python :: 3
Classifier: Programming Language :: Python :: 3 :: Only
Classifier: Programming Language :: Python :: 3.7
Classifier: Programming Language :: Python :: 3.8
Classifier: Programming Language :: Python :: 3.9
Classifier: Programming Language :: Python :: 3.10
Classifier: Programming Language :: Python :: 3.11
Classifier: Programming Language :: Python :: 3.12
Classifier: Programming Language :: Python :: 3.13
Classifier: Topic :: Games/Entertainment
Requires-Python: >=3.7
Requires-Dist: python-dateutil
Requires-Dist: requests
Requires-Dist: simple-term-menu
